sparkserial/__init__.py
sparkserial/__main__.py
sparkserial/main.py
sparkserial/assets/icon.png
sparkserial/core/__init__.py
sparkserial/core/command_manager.py
sparkserial/core/serial_manager.py
sparkserial/gui/__init__.py
sparkserial/gui/converter_dialog.py
sparkserial/gui/main_window.py
sparkserial/gui/styles.py
sparkserial-0.2.1.dist-info/licenses/LICENSE
sparkserial-0.2.1.dist-info/METADATA
sparkserial-0.2.1.dist-info/WHEEL
sparkserial-0.2.1.dist-info/entry_points.txt
sparkserial-0.2.1.dist-info/top_level.txt
sparkserial-0.2.1.dist-info/RECORD
