Metadata-Version: 2.4
Name: sparkserial
Version: 0.2.1
Summary: A lightweight Serial GUI Tool for hardware testing and debugging. Requires USB-to-Serial driver installation based on your adapter.
Author-email: saravanakumar <sarvalece71@gmail.com>
License-Expression: MIT
Keywords: serial,uart,terminal,hardware,debugging,pyqt6,gui
Classifier: Development Status :: 4 - Beta
Classifier: Intended Audience :: Developers
Classifier: Intended Audience :: Science/Research
Classifier: Operating System :: OS Independent
Classifier: Programming Language :: Python :: 3
Classifier: Programming Language :: Python :: 3.11
Classifier: Programming Language :: Python :: 3.12
Classifier: Programming Language :: Python :: 3.13
Classifier: Topic :: Scientific/Engineering
Classifier: Topic :: Terminals :: Serial
Requires-Python: >=3.11
License-File: LICENSE
Requires-Dist: pyqt6>=6.4.0
Requires-Dist: pyserial>=3.5
Provides-Extra: macos
Requires-Dist: pyobjc-framework-cocoa>=9.0; extra == "macos"
Dynamic: license-file
